successive_romaji-0.1.1.dist-info/METADATA
successive_romaji-0.1.1.dist-info/WHEEL
successive_romaji/__pycache__/__init__.cpython-312.pyc
successive_romaji/_lowlevel.pyi
successive_romaji/__init__.py
successive_romaji/_lowlevel.cpython-312-x86_64-linux-gnu.so
successive_romaji-0.1.1.dist-info/RECORD
