Metadata-Version: 2.3
Name: successive-romaji
Version: 0.1.1
Summary: Add your description here
Author-email: nahco314 <nahco3_ta@yahoo.co.jp>
Requires-Python: >=3.8
